optcutfreq/__init__.py
optcutfreq/optcutfreq.py
optcutfreq-0.0.8.dist-info/LICENSE
optcutfreq-0.0.8.dist-info/METADATA
optcutfreq-0.0.8.dist-info/WHEEL
optcutfreq-0.0.8.dist-info/top_level.txt
optcutfreq-0.0.8.dist-info/RECORD
