Metadata-Version: 2.1
Name: optcutfreq
Version: 0.0.8
Summary: Automatic search of optimal filter cutoff frequency based on residual analysis
Home-page: https://github.com/demotu/optcutfreq
Author: Marcos Duarte
Author-email: duartexyz@gmail.com
License: UNKNOWN
Platform: UNKNOWN
Classifier: Programming Language :: Python :: 3
Classifier: License :: OSI Approved :: MIT License
Classifier: Operating System :: OS Independent
Requires-Python: >=3.6
